lockfilepy/__init__.py
lockfilepy/exceptions.py
lockfilepy/lockfile.py
lockfilepy-0.2.0.dist-info/LICENSE
lockfilepy-0.2.0.dist-info/METADATA
lockfilepy-0.2.0.dist-info/WHEEL
lockfilepy-0.2.0.dist-info/top_level.txt
lockfilepy-0.2.0.dist-info/RECORD
